HousingPricePrediction/__init__.py
HousingPricePrediction/exception.py
HousingPricePrediction/logger.py
HousingPricePrediction/components/__init__.py
HousingPricePrediction/components/data_ingestion.py
HousingPricePrediction/components/data_transformation.py
HousingPricePrediction/components/model_evaluation.py
HousingPricePrediction/components/model_trainer.py
HousingPricePrediction/pipelines/__init__.py
HousingPricePrediction/pipelines/prediction_pipeline.py
HousingPricePrediction/pipelines/training_pipeline.py
HousingPricePrediction/utils/__init__.py
HousingPricePrediction/utils/utils.py
uniqueHousePricePrediction-4.0.1.dist-info/LICENSE
uniqueHousePricePrediction-4.0.1.dist-info/METADATA
uniqueHousePricePrediction-4.0.1.dist-info/WHEEL
uniqueHousePricePrediction-4.0.1.dist-info/top_level.txt
uniqueHousePricePrediction-4.0.1.dist-info/RECORD
